ggmcp/__init__.py
ggmcp_fastmcp-0.5.1.dist-info/METADATA
ggmcp_fastmcp-0.5.1.dist-info/WHEEL
ggmcp_fastmcp-0.5.1.dist-info/entry_points.txt
ggmcp_fastmcp-0.5.1.dist-info/licenses/LICENSE
ggmcp_fastmcp-0.5.1.dist-info/RECORD
