Metadata-Version: 2.4
Name: ggmcp-fastmcp
Version: 0.5.1
Summary: MCP server for GitGuardian
Project-URL: Homepage, https://github.com/fastmcp-me/ggmcp#readme
Project-URL: Repository, https://github.com/fastmcp-me/ggmcp.git
Project-URL: Issues, https://github.com/fastmcp-me/ggmcp/issues
Author-email: GitGuardian <support@gitguardian.com>
Maintainer-email: GitGuardian <support@gitguardian.com>
License-Expression: MIT
License-File: LICENSE
Keywords: cli,devsecops,gitguardian,mcp,security-tools
Classifier: Development Status :: 4 - Beta
Classifier: Environment :: Console
Classifier: Intended Audience :: Developers
Classifier: Intended Audience :: End Users/Desktop
Classifier: Natural Language :: English
Classifier: Operating System :: OS Independent
Classifier: Programming Language :: Python
Classifier: Programming Language :: Python :: 3.13
Classifier: Topic :: Security
Requires-Python: >=3.10
Requires-Dist: developer-mcp-server
Requires-Dist: mcp>=1.23.0
Requires-Dist: secops-mcp-server
